auto_pytabs/__init__.py
auto_pytabs/core.py
auto_pytabs/markdown_ext.py
auto_pytabs/mkdocs_plugin.py
auto_pytabs/sphinx_ext.py
auto_pytabs-0.5.0.dist-info/LICENSE
auto_pytabs-0.5.0.dist-info/METADATA
auto_pytabs-0.5.0.dist-info/WHEEL
auto_pytabs-0.5.0.dist-info/entry_points.txt
auto_pytabs-0.5.0.dist-info/RECORD
