Metadata-Version: 2.1
Name: auto-pytabs
Version: 0.5.0
Summary: Automatically generate code examples for different Python versions in mkdocs or Sphinx based documentations
Author: Janek Nouvertné
Author-email: provinzkraut@posteo.de
Requires-Python: >=3.8,<4.0
Classifier: Programming Language :: Python :: 3
Classifier: Programming Language :: Python :: 3.8
Classifier: Programming Language :: Python :: 3.9
Classifier: Programming Language :: Python :: 3.10
Classifier: Programming Language :: Python :: 3.11
Classifier: Programming Language :: Python :: 3.12
Provides-Extra: markdown
Provides-Extra: mkdocs
Provides-Extra: sphinx
Requires-Dist: markdown (>=3.2.1) ; extra == "markdown"
Requires-Dist: mkdocs (>=1.4.2,<2) ; extra == "mkdocs"
Requires-Dist: ruff (>=0.4)
Requires-Dist: sphinx (>=4) ; extra == "sphinx"
